LICENSE
MANIFEST.in
README.md
requirements.txt
setup.py
nlpclean/__init__.py
nlpclean/clean.py
nlpclean/ddup.py
nlpclean/html.py
nlpclean/lang.py
nlpclean/repair.py
nlpclean/table.py
nlpclean.egg-info/PKG-INFO
nlpclean.egg-info/SOURCES.txt
nlpclean.egg-info/dependency_links.txt
nlpclean.egg-info/requires.txt
nlpclean.egg-info/top_level.txt